Metadata-Version: 1.0
Name: aag-probability
Version: 1.9
Summary: Gaussian and Binomial distributions
Home-page: https://github.com/alangordon258/lighthouse
Author: Alan Gordon
Author-email: alan_a_gordon@hotmail.com
License: UNKNOWN
Platform: UNKNOWN
